<?xml version='1.0' encoding='utf-8'?>
<GateDocument>
<!-- The document's features-->

<GateDocumentFeatures>
<Feature>
  <Name className="java.lang.String">MimeType</Name>
  <Value className="java.lang.String">text/plain</Value>
</Feature>
<Feature>
  <Name className="java.lang.String">gate.SourceURL</Name>
  <Value className="java.lang.String">file:/C:/Users/Бустка/Desktop/відгуки%20в%20нотпаді/Chubko_26_Соломія_04122012.txt</Value>
</Feature>
<Feature>
  <Name className="java.lang.String">docNewLineType</Name>
  <Value className="java.lang.String">CRLF</Value>
</Feature>
</GateDocumentFeatures>
<!-- The document content area with serialized nodes -->

<TextWithNodes><Node id="0" />Соломія<Node id="7" /> пише:&#xd;
<Node id="15" />04.12.2012<Node id="25" /> в <Node id="28" />19:47<Node id="33" />&#xd;
Усе дуже сподобалось, було надзвичайно смачно і затишно, обслуговування хороше і взагалі нічого поганого не помітила.<Node id="152" /></TextWithNodes>
<!-- The default annotation set -->

<AnnotationSet>
<Annotation Id="1" Type="token" StartNode="0" EndNode="7">
<Feature>
  <Name className="java.lang.String">morphology</Name>
  <Value className="java.lang.String">Npfsny</Value>
</Feature>
<Feature>
  <Name className="java.lang.String">lemma</Name>
  <Value className="java.lang.String">соломія</Value>
</Feature>
<Feature>
  <Name className="java.lang.String">kind</Name>
  <Value className="java.lang.String">nickname</Value>
</Feature>
<Feature>
  <Name className="java.lang.String">pos</Name>
  <Value className="java.lang.String">N</Value>
</Feature>
</Annotation>
<Annotation Id="2" Type="time" StartNode="15" EndNode="25">
<Feature>
  <Name className="java.lang.String">kind</Name>
  <Value className="java.lang.String">date</Value>
</Feature>
</Annotation>
<Annotation Id="3" Type="time" StartNode="28" EndNode="33">
<Feature>
  <Name className="java.lang.String">kind</Name>
  <Value className="java.lang.String">time</Value>
</Feature>
</Annotation>
</AnnotationSet>

<!-- Named annotation set -->

<AnnotationSet Name="Original markups">
<Annotation Id="0" Type="paragraph" StartNode="0" EndNode="152">
</Annotation>
</AnnotationSet>

</GateDocument>
