<?xml version='1.0' encoding='utf-8'?>
<GateDocument>
<!-- The document's features-->

<GateDocumentFeatures>
<Feature>
  <Name className="java.lang.String">TIKA_CREATOR</Name>
  <Value className="java.lang.String">Nedved</Value>
</Feature>
<Feature>
  <Name className="java.lang.String">AUTHOR</Name>
  <Value className="java.lang.String">Nedved</Value>
</Feature>
<Feature>
  <Name className="java.lang.String">CREATOR</Name>
  <Value className="java.lang.String">Nedved</Value>
</Feature>
<Feature>
  <Name className="java.lang.String">gate.SourceURL</Name>
  <Value className="java.lang.String">file:/D:/ФІЛОЛОГІЯ)/5-ий%20курс/2%20семестр/Романюк/IrynaShtanhretРозраха/Відгуки/Shtanhret_20_Wonder_02.01.2012.txt.docx</Value>
</Feature>
<Feature>
  <Name className="java.lang.String">TIKA_AUTHOR</Name>
  <Value className="java.lang.String">Nedved</Value>
</Feature>
<Feature>
  <Name className="java.lang.String">MimeType</Name>
  <Value className="java.lang.String">application/vnd.openxmlformats-officedocument.wordprocessingml.document</Value>
</Feature>
</GateDocumentFeatures>
<!-- The document content area with serialized nodes -->

<TextWithNodes><Node id="0" />Wonder<Node id="6" />
<Node id="7" />02.01.2012<Node id="17" />,<Node id="18" /> 22:31<Node id="24" />
<Node id="25" />була сьодня в <Node id="39" />Золотій<Node id="46" /> <Node id="47" />Гусі<Node id="51" />: місця багато, інтерєр нормальний, <Node id="87" />офіціанти<Node id="96" /> привітні, хотіли замовити тарілку з<Node id="132" /> <Node id="133" />бастурмою<Node id="142" /> <Node id="143" />яловичиною<Node id="153" /> і <Node id="156" />кониною<Node id="163" />, то сказали що є лише<Node id="185" /> <Node id="186" />бастурма<Node id="194" />, але саму її не продадуть :girl_nea: сумно<Node id="237" />
<Node id="238" />в результаті пила <Node id="256" />чай<Node id="259" /> і <Node id="262" />яблучний<Node id="270" /> <Node id="271" />торт<Node id="275" />, який був поданий на великий тарілці, гарно оформлений <Node id="331" />варенням<Node id="339" /> і десертна вилочка насмак такий собі, але їсти можна<Node id="392" />
<Node id="393" />хотіли попасти в <Node id="410" />піцерію<Node id="417" /> <Node id="418" />Белачао<Node id="425" />, але там було зайнято, отож згадали студентськи роки і пішли в<Node id="488" /> <Node id="489" />піцерію<Node id="496" /> чи це <Node id="503" />кафе<Node id="507" /> <Node id="508" />Кальчо<Node id="514" /> на <Node id="518" />Підвальній<Node id="528" />, ціни дуже бюджетні, відношення нормальне, скажемо так співвідношення ціна - яксть відповідні, чесно<Node id="629" /> <Node id="630" />Кальчо<Node id="636" /> мене порадувало,<Node id="653" /> стіки років<Node id="665" /> а це <Node id="671" />кафе<Node id="675" /> не змінилось :):):)<Node id="695" />
<Node id="696" /></TextWithNodes>
<!-- The default annotation set -->

<AnnotationSet>
<Annotation Id="14" Type="person" StartNode="0" EndNode="6">
<Feature>
  <Name className="java.lang.String">kind</Name>
  <Value className="java.lang.String">nickname</Value>
</Feature>
</Annotation>
<Annotation Id="15" Type="time" StartNode="7" EndNode="17">
<Feature>
  <Name className="java.lang.String">kind</Name>
  <Value className="java.lang.String">date</Value>
</Feature>
</Annotation>
<Annotation Id="17" Type="organization" StartNode="39" EndNode="51">
</Annotation>
<Annotation Id="16" Type="time" StartNode="18" EndNode="24">
<Feature>
  <Name className="java.lang.String">kind</Name>
  <Value className="java.lang.String">time</Value>
</Feature>
</Annotation>
<Annotation Id="19" Type="food" StartNode="256" EndNode="259">
</Annotation>
<Annotation Id="18" Type="person" StartNode="87" EndNode="96">
<Feature>
  <Name className="java.lang.String">kind</Name>
  <Value className="java.lang.String">position</Value>
</Feature>
</Annotation>
<Annotation Id="21" Type="food" StartNode="331" EndNode="339">
</Annotation>
<Annotation Id="20" Type="food" StartNode="262" EndNode="275">
</Annotation>
<Annotation Id="23" Type="organization" StartNode="488" EndNode="496">
</Annotation>
<Annotation Id="22" Type="organization" StartNode="410" EndNode="425">
</Annotation>
<Annotation Id="25" Type="address" StartNode="518" EndNode="528">
<Feature>
  <Name className="java.lang.String">kind</Name>
  <Value className="java.lang.String">street</Value>
</Feature>
</Annotation>
<Annotation Id="24" Type="organization" StartNode="503" EndNode="514">
</Annotation>
<Annotation Id="26" Type="organization" StartNode="629" EndNode="636">
</Annotation>
<Annotation Id="29" Type="time" StartNode="653" EndNode="665">
<Feature>
  <Name className="java.lang.String">kind</Name>
  <Value className="java.lang.String">period</Value>
</Feature>
</Annotation>
<Annotation Id="28" Type="organization" StartNode="671" EndNode="675">
</Annotation>
<Annotation Id="31" Type="food" StartNode="185" EndNode="194">
</Annotation>
<Annotation Id="30" Type="food" StartNode="132" EndNode="163">
</Annotation>
<Annotation Id="34" Type="token" StartNode="87" EndNode="96">
<Feature>
  <Name className="java.lang.String">morphology</Name>
  <Value className="java.lang.String">Ncmpny</Value>
</Feature>
<Feature>
  <Name className="java.lang.String">lemma</Name>
  <Value className="java.lang.String">офіціант</Value>
</Feature>
<Feature>
  <Name className="java.lang.String">pos</Name>
  <Value className="java.lang.String">N</Value>
</Feature>
</Annotation>
<Annotation Id="35" Type="token" StartNode="133" EndNode="142">
<Feature>
  <Name className="java.lang.String">morphology</Name>
  <Value className="java.lang.String">Ncfsin</Value>
</Feature>
<Feature>
  <Name className="java.lang.String">lemma</Name>
  <Value className="java.lang.String">бастурма</Value>
</Feature>
<Feature>
  <Name className="java.lang.String">pos</Name>
  <Value className="java.lang.String">N</Value>
</Feature>
</Annotation>
<Annotation Id="32" Type="token" StartNode="39" EndNode="46">
<Feature>
  <Name className="java.lang.String">morphology</Name>
  <Value className="java.lang.String">Ao--slf</Value>
</Feature>
<Feature>
  <Name className="java.lang.String">lemma</Name>
  <Value className="java.lang.String">золотий</Value>
</Feature>
<Feature>
  <Name className="java.lang.String">pos</Name>
  <Value className="java.lang.String">A</Value>
</Feature>
</Annotation>
<Annotation Id="33" Type="token" StartNode="47" EndNode="51">
<Feature>
  <Name className="java.lang.String">morphology</Name>
  <Value className="java.lang.String">X</Value>
</Feature>
<Feature>
  <Name className="java.lang.String">lemma</Name>
  <Value className="java.lang.String">Гуса</Value>
</Feature>
<Feature>
  <Name className="java.lang.String">pos</Name>
  <Value className="java.lang.String">X</Value>
</Feature>
</Annotation>
<Annotation Id="38" Type="token" StartNode="186" EndNode="194">
<Feature>
  <Name className="java.lang.String">morphology</Name>
  <Value className="java.lang.String">Ncfsnn</Value>
</Feature>
<Feature>
  <Name className="java.lang.String">lemma</Name>
  <Value className="java.lang.String">бастурма</Value>
</Feature>
<Feature>
  <Name className="java.lang.String">pos</Name>
  <Value className="java.lang.String">N</Value>
</Feature>
</Annotation>
<Annotation Id="39" Type="token" StartNode="256" EndNode="259">
<Feature>
  <Name className="java.lang.String">morphology</Name>
  <Value className="java.lang.String">Ncmsan</Value>
</Feature>
<Feature>
  <Name className="java.lang.String">lemma</Name>
  <Value className="java.lang.String">чай</Value>
</Feature>
<Feature>
  <Name className="java.lang.String">pos</Name>
  <Value className="java.lang.String">N</Value>
</Feature>
</Annotation>
<Annotation Id="36" Type="token" StartNode="143" EndNode="153">
<Feature>
  <Name className="java.lang.String">morphology</Name>
  <Value className="java.lang.String">Ncfsin</Value>
</Feature>
<Feature>
  <Name className="java.lang.String">lemma</Name>
  <Value className="java.lang.String">яловичина</Value>
</Feature>
<Feature>
  <Name className="java.lang.String">pos</Name>
  <Value className="java.lang.String">N</Value>
</Feature>
</Annotation>
<Annotation Id="37" Type="token" StartNode="156" EndNode="163">
<Feature>
  <Name className="java.lang.String">morphology</Name>
  <Value className="java.lang.String">Ncfsin</Value>
</Feature>
<Feature>
  <Name className="java.lang.String">lemma</Name>
  <Value className="java.lang.String">конина</Value>
</Feature>
<Feature>
  <Name className="java.lang.String">pos</Name>
  <Value className="java.lang.String">N</Value>
</Feature>
</Annotation>
<Annotation Id="42" Type="token" StartNode="331" EndNode="339">
<Feature>
  <Name className="java.lang.String">morphology</Name>
  <Value className="java.lang.String">Ncnsin</Value>
</Feature>
<Feature>
  <Name className="java.lang.String">lemma</Name>
  <Value className="java.lang.String">варення</Value>
</Feature>
<Feature>
  <Name className="java.lang.String">pos</Name>
  <Value className="java.lang.String">N</Value>
</Feature>
</Annotation>
<Annotation Id="43" Type="token" StartNode="410" EndNode="417">
<Feature>
  <Name className="java.lang.String">morphology</Name>
  <Value className="java.lang.String">Ncfsan</Value>
</Feature>
<Feature>
  <Name className="java.lang.String">lemma</Name>
  <Value className="java.lang.String">піцерія</Value>
</Feature>
<Feature>
  <Name className="java.lang.String">pos</Name>
  <Value className="java.lang.String">N</Value>
</Feature>
</Annotation>
<Annotation Id="40" Type="token" StartNode="271" EndNode="275">
<Feature>
  <Name className="java.lang.String">morphology</Name>
  <Value className="java.lang.String">Ncmsan</Value>
</Feature>
<Feature>
  <Name className="java.lang.String">lemma</Name>
  <Value className="java.lang.String">торт</Value>
</Feature>
<Feature>
  <Name className="java.lang.String">pos</Name>
  <Value className="java.lang.String">N</Value>
</Feature>
</Annotation>
<Annotation Id="41" Type="token" StartNode="262" EndNode="270">
<Feature>
  <Name className="java.lang.String">morphology</Name>
  <Value className="java.lang.String">Ao-msaf</Value>
</Feature>
<Feature>
  <Name className="java.lang.String">lemma</Name>
  <Value className="java.lang.String">яблучний</Value>
</Feature>
<Feature>
  <Name className="java.lang.String">pos</Name>
  <Value className="java.lang.String">A</Value>
</Feature>
</Annotation>
<Annotation Id="46" Type="token" StartNode="503" EndNode="507">
<Feature>
  <Name className="java.lang.String">morphology</Name>
  <Value className="java.lang.String">Ncnsnn</Value>
</Feature>
<Feature>
  <Name className="java.lang.String">lemma</Name>
  <Value className="java.lang.String">кафе</Value>
</Feature>
<Feature>
  <Name className="java.lang.String">pos</Name>
  <Value className="java.lang.String">N</Value>
</Feature>
</Annotation>
<Annotation Id="47" Type="token" StartNode="508" EndNode="514">
<Feature>
  <Name className="java.lang.String">morphology</Name>
  <Value className="java.lang.String">Np-snn</Value>
</Feature>
<Feature>
  <Name className="java.lang.String">lemma</Name>
  <Value className="java.lang.String">Кальчо</Value>
</Feature>
<Feature>
  <Name className="java.lang.String">pos</Name>
  <Value className="java.lang.String">N</Value>
</Feature>
</Annotation>
<Annotation Id="44" Type="token" StartNode="418" EndNode="425">
<Feature>
  <Name className="java.lang.String">morphology</Name>
  <Value className="java.lang.String">Np-snn</Value>
</Feature>
<Feature>
  <Name className="java.lang.String">lemma</Name>
  <Value className="java.lang.String">Белачао</Value>
</Feature>
<Feature>
  <Name className="java.lang.String">pos</Name>
  <Value className="java.lang.String">N</Value>
</Feature>
</Annotation>
<Annotation Id="45" Type="token" StartNode="489" EndNode="496">
<Feature>
  <Name className="java.lang.String">morphology</Name>
  <Value className="java.lang.String">Ncfsan</Value>
</Feature>
<Feature>
  <Name className="java.lang.String">lemma</Name>
  <Value className="java.lang.String">піцерія</Value>
</Feature>
<Feature>
  <Name className="java.lang.String">pos</Name>
  <Value className="java.lang.String">N</Value>
</Feature>
</Annotation>
<Annotation Id="50" Type="token" StartNode="671" EndNode="675">
<Feature>
  <Name className="java.lang.String">morphology</Name>
  <Value className="java.lang.String">Ncnsnn</Value>
</Feature>
<Feature>
  <Name className="java.lang.String">lemma</Name>
  <Value className="java.lang.String">кафе</Value>
</Feature>
<Feature>
  <Name className="java.lang.String">pos</Name>
  <Value className="java.lang.String">N</Value>
</Feature>
</Annotation>
<Annotation Id="49" Type="token" StartNode="630" EndNode="636">
<Feature>
  <Name className="java.lang.String">morphology</Name>
  <Value className="java.lang.String">Np-snn</Value>
</Feature>
<Feature>
  <Name className="java.lang.String">lemma</Name>
  <Value className="java.lang.String">Кальчо</Value>
</Feature>
<Feature>
  <Name className="java.lang.String">pos</Name>
  <Value className="java.lang.String">N</Value>
</Feature>
</Annotation>
<Annotation Id="48" Type="token" StartNode="518" EndNode="528">
<Feature>
  <Name className="java.lang.String">morphology</Name>
  <Value className="java.lang.String">Npfsln</Value>
</Feature>
<Feature>
  <Name className="java.lang.String">lemma</Name>
  <Value className="java.lang.String">Підвальна</Value>
</Feature>
<Feature>
  <Name className="java.lang.String">pos</Name>
  <Value className="java.lang.String">N</Value>
</Feature>
</Annotation>
</AnnotationSet>

<!-- Named annotation set -->

<AnnotationSet Name="Original markups">
<Annotation Id="0" Type="html" StartNode="0" EndNode="695">
</Annotation>
<Annotation Id="1" Type="head" StartNode="0" EndNode="0">
<Feature>
  <Name className="java.lang.String">isEmptyAndSpan</Name>
  <Value className="java.lang.String">true</Value>
</Feature>
</Annotation>
<Annotation Id="2" Type="meta" StartNode="0" EndNode="0">
<Feature>
  <Name className="java.lang.String">content</Name>
  <Value className="java.lang.String">application/vnd.openxmlformats-officedocument.wordprocessingml.document</Value>
</Feature>
<Feature>
  <Name className="java.lang.String">isEmptyAndSpan</Name>
  <Value className="java.lang.String">true</Value>
</Feature>
<Feature>
  <Name className="java.lang.String">name</Name>
  <Value className="java.lang.String">Content-Type</Value>
</Feature>
</Annotation>
<Annotation Id="3" Type="meta" StartNode="0" EndNode="0">
<Feature>
  <Name className="java.lang.String">content</Name>
  <Value className="java.lang.String">Shtanhret_20_Wonder_02.01.2012.txt.docx</Value>
</Feature>
<Feature>
  <Name className="java.lang.String">isEmptyAndSpan</Name>
  <Value className="java.lang.String">true</Value>
</Feature>
<Feature>
  <Name className="java.lang.String">name</Name>
  <Value className="java.lang.String">resourceName</Value>
</Feature>
</Annotation>
<Annotation Id="4" Type="title" StartNode="0" EndNode="0">
<Feature>
  <Name className="java.lang.String">isEmptyAndSpan</Name>
  <Value className="java.lang.String">true</Value>
</Feature>
</Annotation>
<Annotation Id="5" Type="body" StartNode="0" EndNode="695">
</Annotation>
<Annotation Id="6" Type="p" StartNode="0" EndNode="6">
</Annotation>
<Annotation Id="7" Type="p" StartNode="7" EndNode="24">
</Annotation>
<Annotation Id="8" Type="p" StartNode="25" EndNode="237">
</Annotation>
<Annotation Id="9" Type="p" StartNode="238" EndNode="392">
</Annotation>
<Annotation Id="10" Type="p" StartNode="393" EndNode="393">
<Feature>
  <Name className="java.lang.String">isEmptyAndSpan</Name>
  <Value className="java.lang.String">true</Value>
</Feature>
</Annotation>
<Annotation Id="11" Type="p" StartNode="393" EndNode="695">
</Annotation>
<Annotation Id="12" Type="p" StartNode="696" EndNode="696">
<Feature>
  <Name className="java.lang.String">isEmptyAndSpan</Name>
  <Value className="java.lang.String">true</Value>
</Feature>
</Annotation>
<Annotation Id="13" Type="a" StartNode="696" EndNode="696">
<Feature>
  <Name className="java.lang.String">isEmptyAndSpan</Name>
  <Value className="java.lang.String">true</Value>
</Feature>
<Feature>
  <Name className="java.lang.String">name</Name>
  <Value className="java.lang.String">_GoBack</Value>
</Feature>
</Annotation>
</AnnotationSet>

</GateDocument>
